<?xml version="1.0" encoding="ISO-8859-1"?>
 <s:Envelope xmlns:s="http://schemas.xmlsoap.org/soap/envelope/">
      <GetPaikkatilanneDataResponse xmlns="urn:Tieto.HCW.EIS.PaikkatilanneService.ServiceContracts">
         <AcknowledgeRequestStatus xmlns="urn:Tieto.HCW.EIS.PaikkatilanneService.WCFService" xmlns:a="http://schemas.datacontract.org/2004/07/Tieto.HCW.EIS.LISCommon" xmlns:i="http://www.w3.org/2001/XMLSchema-instance">
            <a:ErrorMessage i:nil="true"/>
            <a:ErrorType i:nil="true"/>
            <a:HasOperationFailed>false</a:HasOperationFailed>
         </AcknowledgeRequestStatus>
         <MessageHeader xmlns="urn:Tieto.HCW.EIS.PaikkatilanneService.WCFService" xmlns:a="http://schemas.datacontract.org/2004/07/Tieto.HCW.EIS.LISCommon" xmlns:i="http://www.w3.org/2001/XMLSchema-instance">
            <a:CharacterSet i:nil="true"/>
            <a:DataServiceURL i:nil="true"/>
            <a:MessageID>?</a:MessageID>
            <a:ReceiverApplication i:nil="true"/>
            <a:ReceiverID i:nil="true"/>
            <a:SenderApplication i:nil="true"/>
            <a:SenderID i:nil="true"/>
            <a:TransactionID>?</a:TransactionID>
            <a:UserLanguageCode>?</a:UserLanguageCode>
            <a:VersionNumber>?</a:VersionNumber>
         </MessageHeader>
         <WardStatus xmlns="urn:Tieto.HCW.EIS.PaikkatilanneService.WCFService" xmlns:a="http://schemas.datacontract.org/2004/07/Tieto.HCW.EIS.PaikkatilanneService.DataContracts" xmlns:i="http://www.w3.org/2001/XMLSchema-instance">
            <a:Wards>
               <a:Ward>
                  <a:Organization>4031700001</a:Organization>
                  <a:WardCode>2204Y</a:WardCode>
                  <a:WardName>A22  ortopedian osasto</a:WardName>
                  <a:WardInUse>true</a:WardInUse>
                  <a:Rooms>
                     <a:Room>
                        <a:RoomCode/>
                        <a:RoomName/>
                        <a:RoomType/>
                        <a:RoomInUse>false</a:RoomInUse>
                        <a:Beds>
                           <a:Bed>
                              <a:BedCode/>
                              <a:BedOverplace>true</a:BedOverplace>
                              <a:BedTemporaryClosed/>
                              <a:BedInUse>false</a:BedInUse>
                              <a:Present>
                                 <a:PresentSsn/>
                                 <a:PresentIsolationCode/>
                                 <a:PresentLeavingDate/>
                              </a:Present>
                              <a:Arrival>
                                 <a:ArrivalSSN>090900AA010</a:ArrivalSSN>
                                 <a:ArrivalDate>7.6.2008 0:00:00</a:ArrivalDate>
                              </a:Arrival>
                           </a:Bed>
                           <a:Bed>
                              <a:BedCode/>
                              <a:BedOverplace>true</a:BedOverplace>
                              <a:BedTemporaryClosed/>
                              <a:BedInUse>false</a:BedInUse>
                              <a:Present>
                                 <a:PresentSsn/>
                                 <a:PresentIsolationCode/>
                                 <a:PresentLeavingDate/>
                              </a:Present>
                              <a:Arrival>
                                 <a:ArrivalSSN>190180-900R</a:ArrivalSSN>
                                 <a:ArrivalDate>29.3.2012 0:00:00</a:ArrivalDate>
                              </a:Arrival>
                           </a:Bed>
                           <a:Bed>
                              <a:BedCode/>
                              <a:BedOverplace>true</a:BedOverplace>
                              <a:BedTemporaryClosed/>
                              <a:BedInUse>false</a:BedInUse>
                              <a:Present>
                                 <a:PresentSsn/>
                                 <a:PresentIsolationCode/>
                                 <a:PresentLeavingDate/>
                              </a:Present>
                              <a:Arrival>
                                 <a:ArrivalSSN>191277-A011</a:ArrivalSSN>
                                 <a:ArrivalDate>19.2.2008 0:00:00</a:ArrivalDate>
                              </a:Arrival>
                           </a:Bed>
                           <a:Bed>
                              <a:BedCode/>
                              <a:BedOverplace>true</a:BedOverplace>
                              <a:BedTemporaryClosed/>
                              <a:BedInUse>false</a:BedInUse>
                              <a:Present>
                                 <a:PresentSsn/>
                                 <a:PresentIsolationCode/>
                                 <a:PresentLeavingDate/>
                              </a:Present>
                              <a:Arrival>
                                 <a:ArrivalSSN>220808A900R</a:ArrivalSSN>
                                 <a:ArrivalDate>29.3.2012 0:00:00</a:ArrivalDate>
                              </a:Arrival>
                           </a:Bed>
                           <a:Bed>
                              <a:BedCode/>
                              <a:BedOverplace>true</a:BedOverplace>
                              <a:BedTemporaryClosed/>
                              <a:BedInUse>false</a:BedInUse>
                              <a:Present>
                                 <a:PresentSsn/>
                                 <a:PresentIsolationCode/>
                                 <a:PresentLeavingDate/>
                              </a:Present>
                              <a:Arrival>
                                 <a:ArrivalSSN>271136-A010</a:ArrivalSSN>
                                 <a:ArrivalDate>10.3.2008 0:00:00</a:ArrivalDate>
                              </a:Arrival>
                           </a:Bed>
                           <a:Bed>
                              <a:BedCode/>
                              <a:BedOverplace>false</a:BedOverplace>
                              <a:BedTemporaryClosed/>
                              <a:BedInUse>false</a:BedInUse>
                              <a:Present>
                                 <a:PresentSsn/>
                                 <a:PresentIsolationCode/>
                                 <a:PresentLeavingDate/>
                              </a:Present>
                              <a:Arrival>
                                 <a:ArrivalSSN>090870-A024</a:ArrivalSSN>
                                 <a:ArrivalDate>23.10.2012 9:00:00</a:ArrivalDate>
                              </a:Arrival>
                           </a:Bed>
                           <a:Bed>
                              <a:BedCode/>
                              <a:BedOverplace>false</a:BedOverplace>
                              <a:BedTemporaryClosed/>
                              <a:BedInUse>false</a:BedInUse>
                              <a:Present>
                                 <a:PresentSsn/>
                                 <a:PresentIsolationCode/>
                                 <a:PresentLeavingDate/>
                              </a:Present>
                              <a:Arrival>
                                 <a:ArrivalSSN>090870-A024</a:ArrivalSSN>
                                 <a:ArrivalDate>23.10.2012 9:30:00</a:ArrivalDate>
                              </a:Arrival>
                           </a:Bed>
                        </a:Beds>
                     </a:Room>
                     <a:Room>
                        <a:RoomCode>31</a:RoomCode>
                        <a:RoomName>H31</a:RoomName>
                        <a:RoomType>S</a:RoomType>
                        <a:RoomInUse>true</a:RoomInUse>
                        <a:Beds>
                           <a:Bed>
                              <a:BedCode>01</a:BedCode>
                              <a:BedOverplace>false</a:BedOverplace>
                              <a:BedTemporaryClosed/>
                              <a:BedInUse>true</a:BedInUse>
                              <a:Present>
                                 <a:PresentSsn/>
                                 <a:PresentIsolationCode/>
                                 <a:PresentLeavingDate/>
                              </a:Present>
                              <a:Arrival>
                                 <a:ArrivalSSN/>
                                 <a:ArrivalDate/>
                              </a:Arrival>
                           </a:Bed>
                           <a:Bed>
                              <a:BedCode>02</a:BedCode>
                              <a:BedOverplace>false</a:BedOverplace>
                              <a:BedTemporaryClosed/>
                              <a:BedInUse>true</a:BedInUse>
                              <a:Present>
                                 <a:PresentSsn/>
                                 <a:PresentIsolationCode/>
                                 <a:PresentLeavingDate/>
                              </a:Present>
                              <a:Arrival>
                                 <a:ArrivalSSN/>
                                 <a:ArrivalDate/>
                              </a:Arrival>
                           </a:Bed>
                        </a:Beds>
                     </a:Room>
                     <a:Room>
                        <a:RoomCode>32</a:RoomCode>
                        <a:RoomName>H32</a:RoomName>
                        <a:RoomType>S</a:RoomType>
                        <a:RoomInUse>true</a:RoomInUse>
                        <a:Beds>
                           <a:Bed>
                              <a:BedCode>01</a:BedCode>
                              <a:BedOverplace>false</a:BedOverplace>
                              <a:BedTemporaryClosed/>
                              <a:BedInUse>true</a:BedInUse>
                              <a:Present>
                                 <a:PresentSsn>050505A902M</a:PresentSsn>
                                 <a:PresentIsolationCode></a:PresentIsolationCode>
                                 <a:PresentLeavingDate/>
                              </a:Present>
                              <a:Arrival>
                                 <a:ArrivalSSN/>
                                 <a:ArrivalDate/>
                              </a:Arrival>
                           </a:Bed>
                           <a:Bed>
                              <a:BedCode>02</a:BedCode>
                              <a:BedOverplace>false</a:BedOverplace>
                              <a:BedTemporaryClosed/>
                              <a:BedInUse>true</a:BedInUse>
                              <a:Present>
                                 <a:PresentSsn>251177-A020</a:PresentSsn>
                                 <a:PresentIsolationCode></a:PresentIsolationCode>
                                 <a:PresentLeavingDate>26.11.2011 0:00:00</a:PresentLeavingDate>
                              </a:Present>
                              <a:Arrival>
                                 <a:ArrivalSSN/>
                                 <a:ArrivalDate/>
                              </a:Arrival>
                           </a:Bed>
                        </a:Beds>
                     </a:Room>
                     <a:Room>
                        <a:RoomCode>33</a:RoomCode>
                        <a:RoomName>H33</a:RoomName>
                        <a:RoomType>S</a:RoomType>
                        <a:RoomInUse>true</a:RoomInUse>
                        <a:Beds>
                           <a:Bed>
                              <a:BedCode>01</a:BedCode>
                              <a:BedOverplace>false</a:BedOverplace>
                              <a:BedTemporaryClosed/>
                              <a:BedInUse>true</a:BedInUse>
                              <a:Present>
                                 <a:PresentSsn/>
                                 <a:PresentIsolationCode/>
                                 <a:PresentLeavingDate/>
                              </a:Present>
                              <a:Arrival>
                                 <a:ArrivalSSN/>
                                 <a:ArrivalDate/>
                              </a:Arrival>
                           </a:Bed>
                           <a:Bed>
                              <a:BedCode>02</a:BedCode>
                              <a:BedOverplace>false</a:BedOverplace>
                              <a:BedTemporaryClosed/>
                              <a:BedInUse>true</a:BedInUse>
                              <a:Present>
                                 <a:PresentSsn/>
                                 <a:PresentIsolationCode/>
                                 <a:PresentLeavingDate/>
                              </a:Present>
                              <a:Arrival>
                                 <a:ArrivalSSN/>
                                 <a:ArrivalDate/>
                              </a:Arrival>
                           </a:Bed>
                        </a:Beds>
                     </a:Room>
                     <a:Room>
                        <a:RoomCode>41</a:RoomCode>
                        <a:RoomName>H41</a:RoomName>
                        <a:RoomType>S</a:RoomType>
                        <a:RoomInUse>true</a:RoomInUse>
                        <a:Beds>
                           <a:Bed>
                              <a:BedCode>01</a:BedCode>
                              <a:BedOverplace>false</a:BedOverplace>
                              <a:BedTemporaryClosed/>
                              <a:BedInUse>true</a:BedInUse>
                              <a:Present>
                                 <a:PresentSsn>140962-901B</a:PresentSsn>
                                 <a:PresentIsolationCode></a:PresentIsolationCode>
                                 <a:PresentLeavingDate/>
                              </a:Present>
                              <a:Arrival>
                                 <a:ArrivalSSN/>
                                 <a:ArrivalDate/>
                              </a:Arrival>
                           </a:Bed>
                           <a:Bed>
                              <a:BedCode>02</a:BedCode>
                              <a:BedOverplace>false</a:BedOverplace>
                              <a:BedTemporaryClosed/>
                              <a:BedInUse>true</a:BedInUse>
                              <a:Present>
                                 <a:PresentSsn>110522-A010</a:PresentSsn>
                                 <a:PresentIsolationCode></a:PresentIsolationCode>
                                 <a:PresentLeavingDate/>
                              </a:Present>
                              <a:Arrival>
                                 <a:ArrivalSSN/>
                                 <a:ArrivalDate/>
                              </a:Arrival>
                           </a:Bed>
                        </a:Beds>
                     </a:Room>
                     <a:Room>
                        <a:RoomCode>42</a:RoomCode>
                        <a:RoomName>H42</a:RoomName>
                        <a:RoomType>S</a:RoomType>
                        <a:RoomInUse>true</a:RoomInUse>
                        <a:Beds>
                           <a:Bed>
                              <a:BedCode>01</a:BedCode>
                              <a:BedOverplace>false</a:BedOverplace>
                              <a:BedTemporaryClosed/>
                              <a:BedInUse>true</a:BedInUse>
                              <a:Present>
                                 <a:PresentSsn/>
                                 <a:PresentIsolationCode/>
                                 <a:PresentLeavingDate/>
                              </a:Present>
                              <a:Arrival>
                                 <a:ArrivalSSN>101044-901X</a:ArrivalSSN>
                                 <a:ArrivalDate>19.4.2012 0:00:00</a:ArrivalDate>
                              </a:Arrival>
                           </a:Bed>
                           <a:Bed>
                              <a:BedCode>02</a:BedCode>
                              <a:BedOverplace>false</a:BedOverplace>
                              <a:BedTemporaryClosed/>
                              <a:BedInUse>true</a:BedInUse>
                              <a:Present>
                                 <a:PresentSsn/>
                                 <a:PresentIsolationCode/>
                                 <a:PresentLeavingDate/>
                              </a:Present>
                              <a:Arrival>
                                 <a:ArrivalSSN/>
                                 <a:ArrivalDate/>
                              </a:Arrival>
                           </a:Bed>
                        </a:Beds>
                     </a:Room>
                     <a:Room>
                        <a:RoomCode>43</a:RoomCode>
                        <a:RoomName>H43</a:RoomName>
                        <a:RoomType>S</a:RoomType>
                        <a:RoomInUse>true</a:RoomInUse>
                        <a:Beds>
                           <a:Bed>
                              <a:BedCode>01</a:BedCode>
                              <a:BedOverplace>false</a:BedOverplace>
                              <a:BedTemporaryClosed/>
                              <a:BedInUse>true</a:BedInUse>
                              <a:Present>
                                 <a:PresentSsn/>
                                 <a:PresentIsolationCode/>
                                 <a:PresentLeavingDate/>
                              </a:Present>
                              <a:Arrival>
                                 <a:ArrivalSSN/>
                                 <a:ArrivalDate/>
                              </a:Arrival>
                           </a:Bed>
                           <a:Bed>
                              <a:BedCode>02</a:BedCode>
                              <a:BedOverplace>false</a:BedOverplace>
                              <a:BedTemporaryClosed/>
                              <a:BedInUse>true</a:BedInUse>
                              <a:Present>
                                 <a:PresentSsn/>
                                 <a:PresentIsolationCode/>
                                 <a:PresentLeavingDate/>
                              </a:Present>
                              <a:Arrival>
                                 <a:ArrivalSSN/>
                                 <a:ArrivalDate/>
                              </a:Arrival>
                           </a:Bed>
                        </a:Beds>
                     </a:Room>
                  </a:Rooms>
               </a:Ward>
            </a:Wards>
            <a:Timestamp>2013-04-23T15:43:27</a:Timestamp>
         </WardStatus>

      </GetPaikkatilanneDataResponse>
</s:Envelope>